data_entry2/__init__.py
data_entry2/data_entry2.py
data_entry2-0.1.9.dist-info/licenses/LICENSE
data_entry2-0.1.9.dist-info/METADATA
data_entry2-0.1.9.dist-info/WHEEL
data_entry2-0.1.9.dist-info/top_level.txt
data_entry2-0.1.9.dist-info/RECORD
