Metadata-Version: 2.4
Name: data_entry2
Version: 0.1.9
Summary: Tool for spreadsheet-like data entry in Jupyter notebooks
Author-email: Carl Michal <michal@physics.ubc.ca>
Project-URL: Homepage, https://www.phas.ubc.ca/~michal/data_entry2
Classifier: Development Status :: 3 - Alpha
Classifier: Intended Audience :: Science/Research
Classifier: Intended Audience :: Education
Classifier: License :: OSI Approved :: GNU General Public License v3 (GPLv3)
Classifier: Programming Language :: Python :: 3
Requires-Python: >=3.7
License-File: LICENSE
Requires-Dist: ipydatagrid
Dynamic: license-file
